{
    "features": [
        "Basic_meta",
        "Basic_ts",
        "TimeSeriesFeatures_cesium_common",
        "TimeSeriesFeatures_cesium_cad",
        "Basic_fluxfactor",
        "Basic_fluxfactor_passband",
        "DiffPeak",
        "TimeSeriesFeatures_cesium_freq",
        "TimeFromPeak",
        "Basic_fluxdiff",
        "Basic_fluxdiff_passband"
    ],
    "cv": {
        "method": "StratifiedKFold",
        "n_splits": 5,
        "random_state": 71
    },
    "gal_model": {
        "name": "lightgbm",
        "model_params": {
            "boosting_type": "gbdt",
            "objective": "multiclass",
            "num_class": -1,
            "metric": "multi_logloss",
            "learning_rate": 0.05,
            "num_leaves": 100,
            "max_depth": -1,
            "subsample": 1.0,
            "colsample_bytree": 0.6,
            "reg_alpha": 5,
            "reg_lambda": 10,
            "min_split_gain": 0.5,
            "min_child_weight": 10,
            "n_estimators": 1000,
            "seed": 71,
            "bagging_seed": 71,
            "feature_fraction_seed": 71,
            "drop_seed": 71,
            "random_state": 71,
            "verbose": -1
        },
        "train_params": {
            "early_stopping_rounds": 100,
            "verbose": 100
        }
    },
    "exgal_model": {
        "name": "lightgbm",
        "model_params": {
            "boosting_type": "gbdt",
            "objective": "multiclass",
            "num_class": 9,
            "metric": "multi_logloss",
            "learning_rate": 0.05,
            "num_leaves": 100,
            "max_depth": -1,
            "subsample": 1.0,
            "colsample_bytree": 0.6,
            "reg_alpha": 5,
            "reg_lambda": 10,
            "min_split_gain": 0.5,
            "min_child_weight": 10,
            "n_estimators": 1000,
            "seed": 71,
            "bagging_seed": 71,
            "feature_fraction_seed": 71,
            "drop_seed": 71,
            "random_state": 71,
            "verbose": -1
        },
        "train_params": {
            "early_stopping_rounds": 100,
            "verbose": 100
        }
    },
    "dataset": {
        "input_directory": "data/input/",
        "intermediate_directory": "data/interim/",
        "feature_directory": "data/feature/",
        "output_directory": "data/output/",
        "files": {
            "meta": {
                "train": "training_set_metadata.csv",
                "test": "test_set_metadata.csv"
            },
            "ts": {
                "train": "training_set.csv",
                "test_sample": "test_set_sample.csv",
                "test": "test_set.csv"
            }
        }
    },
    "args": {
        "config": "configs/lightgbm_35.json",
        "debug_mode": false,
        "select": false,
        "drop": false,
        "iter": true,
        "out": "output_35"
    },
    "evals_result_gal": {
        "oof_score": 0.1611954632989563,
        "cv_score": {
            "cv1": {
                "train": {
                    "multi_logloss": 0.07275990759955939,
                    "wloss": 0.07275990742746337
                },
                "valid": {
                    "multi_logloss": 0.1325465236171317,
                    "wloss": 0.20100798267837472
                }
            },
            "cv2": {
                "train": {
                    "multi_logloss": 0.0706756674339304,
                    "wloss": 0.0706756674437274
                },
                "valid": {
                    "multi_logloss": 0.10802924785248919,
                    "wloss": 0.12275296878773409
                }
            },
            "cv3": {
                "train": {
                    "multi_logloss": 0.06908779686446823,
                    "wloss": 0.06908779684740592
                },
                "valid": {
                    "multi_logloss": 0.12122428077729559,
                    "wloss": 0.1567635616133363
                }
            },
            "cv4": {
                "train": {
                    "multi_logloss": 0.0725100569832461,
                    "wloss": 0.07251005696165574
                },
                "valid": {
                    "multi_logloss": 0.11334810923035382,
                    "wloss": 0.15899725988854166
                }
            },
            "cv5": {
                "train": {
                    "multi_logloss": 0.06931415196046906,
                    "wloss": 0.06931415241348095
                },
                "valid": {
                    "multi_logloss": 0.12925089832446884,
                    "wloss": 0.16688218242269612
                }
            }
        },
        "best_iteration": 169.6,
        "n_features": 60,
        "feature_importance": {
            "qso_log_chi2_qsonu_u": 152.4,
            "diff_mjd_maxmin_detected1": 129.6,
            "median_absolute_deviation_r": 103.6,
            "skew_r": 101.2,
            "flux_by_flux_ratio_sq_skew": 97.8,
            "flux_skew": 96.2,
            "fluxdiff_min_detected1": 83.0,
            "median_absolute_deviation_g": 74.6,
            "period_fast_y": 72.8,
            "flux_err_max_detected1": 69.0,
            "fluxdiff_median_detected1": 63.8,
            "skew_i": 63.6,
            "flux_skew_detected1": 63.6,
            "median_absolute_deviation_y": 61.8,
            "percent_close_to_median_y": 59.2,
            "mean_z": 58.8,
            "period_fast_z": 57.2,
            "std_y": 56.0,
            "skew_z": 55.0,
            "period_fast_r": 51.8,
            "percent_amplitude_r": 50.2,
            "flux_min_detected1": 50.2,
            "flux_median": 50.0,
            "period_fast_i": 49.0,
            "__freq_varrat___5_": 48.4,
            "skew_g": 45.4,
            "stetson_j_y": 44.8,
            "percent_close_to_median_z": 44.6,
            "amplitude_z": 43.4,
            "stetson_k_y": 43.4,
            "minimum_g": 42.8,
            "stetson_k_z": 41.2,
            "stetson_k_i": 41.0,
            "maximum_u": 38.4,
            "flux_percentile_ratio_mid50_g": 38.0,
            "peakpoint_pass2-pass4": 37.2,
            "__freq_varrat___2_": 37.2,
            "flux_percentile_ratio_mid35_g": 35.4,
            "flux_percentile_ratio_mid20_g": 33.8,
            "flux_err_std_detected1": 33.4,
            "peakpoint_pass3-pass5": 33.4,
            "qso_log_chi2_qsonu_r": 32.6,
            "qso_log_chi2_qsonu_y": 31.2,
            "maximum_r": 30.0,
            "weighted_average_y": 29.8,
            "flux_dif2": 29.0,
            "percent_amplitude_g": 29.0,
            "detected_mean": 28.8,
            "amplitude_u": 28.6,
            "maximum_y": 28.2,
            "median_y": 27.6,
            "__freq2_amplitude3___3_": 25.8,
            "flux_ratio_sq_skew": 24.6,
            "flux_by_flux_ratio_sq_skew_detected1": 23.6,
            "__freq_varrat___1_": 23.2,
            "percent_difference_flux_percentile_r": 22.6,
            "__freq_varrat___4_": 21.2,
            "minimum_y": 20.8,
            "stetson_j_g": 19.2,
            "percent_close_to_median_i": 18.2
        }
    },
    "evals_result_exgal": {
        "oof_score": 0.7923989497210905,
        "cv_score": {
            "cv1": {
                "train": {
                    "multi_logloss": 0.3677269154734606,
                    "wloss": 0.36772691956331044
                },
                "valid": {
                    "multi_logloss": 0.9837744147175961,
                    "wloss": 0.8058129520921353
                }
            },
            "cv2": {
                "train": {
                    "multi_logloss": 0.3755036695318242,
                    "wloss": 0.3755036738178589
                },
                "valid": {
                    "multi_logloss": 0.9256271334172342,
                    "wloss": 0.7219248050837882
                }
            },
            "cv3": {
                "train": {
                    "multi_logloss": 0.3649558001473997,
                    "wloss": 0.364955801221709
                },
                "valid": {
                    "multi_logloss": 0.9923266885433925,
                    "wloss": 0.8120588551792005
                }
            },
            "cv4": {
                "train": {
                    "multi_logloss": 0.36926991201579523,
                    "wloss": 0.369269911018632
                },
                "valid": {
                    "multi_logloss": 0.9692022599534305,
                    "wloss": 0.8260464946341359
                }
            },
            "cv5": {
                "train": {
                    "multi_logloss": 0.36559689972437975,
                    "wloss": 0.3655969043033553
                },
                "valid": {
                    "multi_logloss": 0.9624933847022618,
                    "wloss": 0.7972143422334278
                }
            }
        },
        "best_iteration": 259.6,
        "n_features": 100,
        "feature_importance": {
            "diff_mjd_maxmin_detected1": 702.4,
            "median_absolute_deviation_g": 293.2,
            "flux_std_detected1": 276.2,
            "flux_median_fluxfactor": 275.4,
            "flux_dif2_4_fluxfactor": 267.4,
            "period_fast_i": 262.2,
            "stetson_k_g": 262.0,
            "flux_min_detected1": 261.4,
            "flux_w_mean_0_fluxfactor": 261.2,
            "median_r": 260.2,
            "period_fast_g": 256.4,
            "period_fast_r": 254.4,
            "flux_dif2": 253.2,
            "flux_dif3": 250.8,
            "fluxdiff_min_2": 250.2,
            "distmod": 243.2,
            "period_fast_z": 242.8,
            "flux_skew_detected1": 242.6,
            "fluxdiff_std_detected1": 242.6,
            "flux_skew": 242.6,
            "flux_w_mean_1_fluxfactor": 235.2,
            "fluxdiff_median_detected1": 234.2,
            "period_fast_u": 233.4,
            "mean_y": 233.0,
            "mean_u": 225.8,
            "hostgal_photoz_err": 225.2,
            "flux_by_flux_ratio_sq_skew": 220.2,
            "weighted_average_u": 219.0,
            "fluxdiff_skew_detected1": 214.6,
            "peakpoint_pass3-pass5": 214.0,
            "time_from_peak_after_thres0.2_pass3": 211.8,
            "__freq_varrat___0_": 209.6,
            "flux_dif3_2_fluxfactor": 206.8,
            "hostgal_photoz_certain": 206.6,
            "time_from_peak_after_thres0.2_pass4": 203.4,
            "fluxdiff_max_detected1": 201.8,
            "flux_w_mean_5_fluxfactor": 200.8,
            "__freq_varrat___4_": 197.0,
            "flux_w_mean_2_fluxfactor": 194.6,
            "median_absolute_deviation_r": 194.6,
            "flux_dif3_detected1": 194.2,
            "stetson_k_r": 189.6,
            "flux_std_detected1_fluxfactor": 188.6,
            "weighted_average_g": 187.4,
            "time_from_peak_after_thres0.3_pass2": 187.0,
            "flux_by_flux_ratio_sq_sum_1_fluxfactor": 183.6,
            "qso_log_chi2_qsonu_u": 181.0,
            "stetson_j_u": 180.6,
            "maximum_u": 180.2,
            "flux_w_mean_detected1_fluxfactor": 178.8,
            "__freq_varrat___1_": 177.2,
            "flux_dif2_3_fluxfactor": 177.2,
            "median_g": 176.4,
            "flux_dif2_1_fluxfactor": 175.4,
            "fluxdiff_dif2_detected1": 174.0,
            "time_from_peak_after_thres0.3_pass4": 171.8,
            "skew_i": 170.6,
            "percent_close_to_median_r": 167.4,
            "flux_err_skew_detected1": 166.6,
            "qso_log_chi2_qsonu_y": 165.4,
            "peakpoint_pass1-pass4": 163.8,
            "skew_z": 162.8,
            "flux_ratio_sq_sum_0_fluxfactor": 162.0,
            "weighted_average_y": 161.8,
            "__freq_varrat___5_": 161.0,
            "skew_y": 158.8,
            "peakpoint_pass2-pass4": 157.0,
            "__freq_varrat___2_": 155.8,
            "std_u": 155.6,
            "time_from_peak_after_thres0.3_pass3": 154.2,
            "peakpoint_pass1-pass5": 153.0,
            "flux_mean_fluxfactor": 153.0,
            "flux_max_detected1_fluxfactor": 152.0,
            "flux_diff_fluxfactor": 151.6,
            "flux_by_flux_ratio_sq_sum_5_fluxfactor": 150.4,
            "flux_err_max_detected1_fluxfactor": 150.4,
            "peakpoint_pass2-pass5": 149.8,
            "hostgal_photoz": 149.4,
            "time_from_peak_after_thres0.1_pass2": 147.8,
            "fluxdiff_skew_2": 147.0,
            "period_fast_y": 144.6,
            "flux_by_flux_ratio_sq_sum_0_fluxfactor": 143.8,
            "flux_err_min_fluxfactor": 143.2,
            "qso_log_chi2nuNULL_chi2nu_r": 140.2,
            "stetson_k_u": 137.4,
            "peakpoint_pass0-pass3": 134.6,
            "time_from_peak_after_thres0.2_pass2": 133.8,
            "__freq3_freq___2_": 133.0,
            "skew_r": 131.4,
            "flux_dif2_2_fluxfactor": 126.8,
            "flux_w_mean_4_fluxfactor": 126.6,
            "skew_u": 123.6,
            "peakpoint_pass0-pass4": 121.8,
            "flux_dif2_detected1": 119.8,
            "flux_min_detected1_fluxfactor": 114.0,
            "time_from_peak_after_thres0.4_pass3": 114.0,
            "flux_max_fluxfactor": 106.8,
            "flux_skew_fluxfactor": 97.6,
            "flux_mean_detected1_fluxfactor": 94.6,
            "flux_std_fluxfactor": 93.8
        }
    },
    "total_oof_score": 0.5952355003870722,
    "pred_result": {
        "class_99_mean": 0.14000000000000634,
        "class_99_std": 0.05075564797383641
    }
}